altimetry/__init__.py
altimetry/config/__init__.py
altimetry/config/defaults.py
altimetry/data/__init__.py
altimetry/data/alti_data.py
altimetry/data/hydro.py
altimetry/data/hydro_nc.py
altimetry/data/rs_data.py
altimetry/externals/__init__.py
altimetry/externals/cptmaps.py
altimetry/externals/esutils_stat.py
altimetry/tools/__init__.py
altimetry/tools/altimetry_tools.py
altimetry/tools/dates.py
altimetry/tools/distance_matrix.py
altimetry/tools/interp_tools.py
altimetry/tools/loess.py
altimetry/tools/map_tools.py
altimetry/tools/nctools.py
altimetry/tools/nctools_nc.py
altimetry/tools/others.py
altimetry/tools/spatial_tools.py
altimetry/tools/spectrum.py
altimetry/tools/twoD_tools.py
py_altimetry-0.3.2.post1.data/scripts/cdf_merge.py
py_altimetry-0.3.2.post1.data/scripts/j2_spectrum.py
py_altimetry-0.3.2.post1.data/scripts/spectral_tapering.py
py_altimetry-0.3.2.post1.dist-info/DESCRIPTION.rst
py_altimetry-0.3.2.post1.dist-info/METADATA
py_altimetry-0.3.2.post1.dist-info/RECORD
py_altimetry-0.3.2.post1.dist-info/WHEEL
py_altimetry-0.3.2.post1.dist-info/metadata.json
py_altimetry-0.3.2.post1.dist-info/top_level.txt
