Metadata-Version: 2.0
Name: py-altimetry
Version: 0.3.2.post1
Summary: PyAltimetry: Python tools for altimetry data and much more
Home-page: https://code.google.com/p/py-altiwaves/
Author: R. Dussurget
Author-email: renaud.dussurget@gmail.com
License: LICENSE.TXT
Platform: UNKNOWN
Requires-Dist: NetCDF4
Requires-Dist: matplotlib
Requires-Dist: numpy
Requires-Dist: scipy
